symbolic_compartmental_model/__init__.py
symbolic_compartmental_model/symbolic_compartmental_model.py
symbolic_compartmental_model-0.0.3.dist-info/licenses/LICENSE
symbolic_compartmental_model-0.0.3.dist-info/METADATA
symbolic_compartmental_model-0.0.3.dist-info/WHEEL
symbolic_compartmental_model-0.0.3.dist-info/top_level.txt
symbolic_compartmental_model-0.0.3.dist-info/zip-safe
symbolic_compartmental_model-0.0.3.dist-info/RECORD
